<?xml version="1.0" encoding="UTF-8"?>
<PromotionReports>
  <Promotion>
    <ID>1</ID>
    <Title>Summer Sale</Title>
    <StartDate>2024-09-22</StartDate>
    <EndDate>2024-10-22</EndDate>
    <RevenueDetails>
      <TotalRevenue>1,100.00</TotalRevenue>
      <AverageOrderValueWith>550.00</AverageOrderValueWith>
      <AverageOrderValueWithout>120.00</AverageOrderValueWithout>
    </RevenueDetails>
    <ProductsSold>4</ProductsSold>
    <MonthlyRevenue>
      <Month>
        <MonthName>2024-08</MonthName>
        <Revenue>800.00</Revenue>
      </Month>
      <Month>
        <MonthName>2024-09</MonthName>
        <Revenue>300.00</Revenue>
      </Month>
    </MonthlyRevenue>
  </Promotion>
  <Promotion>
    <ID>2</ID>
    <Title>Winter Sale</Title>
    <StartDate>2024-09-22</StartDate>
    <EndDate>2024-11-21</EndDate>
    <RevenueDetails>
      <TotalRevenue>0.00</TotalRevenue>
      <AverageOrderValueWith>0.00</AverageOrderValueWith>
      <AverageOrderValueWithout>120.00</AverageOrderValueWithout>
    </RevenueDetails>
    <ProductsSold>0</ProductsSold>
    <MonthlyRevenue/>
  </Promotion>
</PromotionReports>
